mypiptestqwe/__init__.py
mypiptestqwe-0.1.0.dist-info/WHEEL
mypiptestqwe-0.1.0.dist-info/METADATA
mypiptestqwe-0.1.0.dist-info/RECORD
