Metadata-Version: 2.1
Name: mypiptestqwe
Version: 0.1.0
Summary: Let's find some podcasts!
Author: Alexandr
Author-email: zbc@mail.ru
Classifier: License :: OSI Approved :: MIT License
